CHANGES.rst
LICENSE.txt
MANIFEST.in
README.rst
pyproject.toml
requirements.txt
setup.py
compyle/__init__.py
compyle/api.py
compyle/array.py
compyle/ast_utils.py
compyle/capture_stream.py
compyle/config.py
compyle/cuda.py
compyle/cython_generator.py
compyle/ext_module.py
compyle/extern.py
compyle/jit.py
compyle/low_level.py
compyle/opencl.py
compyle/parallel.py
compyle/profile.py
compyle/sort.py
compyle/template.py
compyle/translator.py
compyle/transpiler.py
compyle/types.py
compyle/utils.py
compyle.egg-info/PKG-INFO
compyle.egg-info/SOURCES.txt
compyle.egg-info/dependency_links.txt
compyle.egg-info/requires.txt
compyle.egg-info/top_level.txt
compyle/tests/__init__.py
compyle/tests/py3_code.py
compyle/tests/test_array.py
compyle/tests/test_ast_utils.py
compyle/tests/test_capture_stream.py
compyle/tests/test_change_backend.py
compyle/tests/test_config.py
compyle/tests/test_cuda.py
compyle/tests/test_cython_generator.py
compyle/tests/test_ext_module.py
compyle/tests/test_gpu_struct.py
compyle/tests/test_jit.py
compyle/tests/test_low_level.py
compyle/tests/test_parallel.py
compyle/tests/test_profile.py
compyle/tests/test_template.py
compyle/tests/test_translator.py
compyle/tests/test_transpiler.py
compyle/tests/test_types.py
compyle/tests/test_utils.py
compyle/thrust/__init__.py
compyle/thrust/sort.pyx
docs/source/conf.py
docs/source/details.rst
docs/source/index.rst
docs/source/installation.rst
docs/source/overview.rst
examples/axpb.py
examples/axpb_jit.py
examples/bench_vm.py
examples/julia_set.py
examples/laplace.py
examples/vm_elementwise.py
examples/vm_elementwise_jit.py
examples/vm_kernel.py
examples/vm_numba.py
examples/molecular_dynamics/README.rst
examples/molecular_dynamics/md_nnps.py
examples/molecular_dynamics/md_simple.py
examples/molecular_dynamics/nnps.py
examples/molecular_dynamics/nnps_kernels.py
examples/molecular_dynamics/performance_comparison.py
examples/molecular_dynamics/3D/compare_results.py
examples/molecular_dynamics/3D/hoomd_periodic.py
examples/molecular_dynamics/3D/md_nnps.py
examples/molecular_dynamics/3D/md_nnps_periodic.py
examples/molecular_dynamics/3D/md_simple.py
